{
"autoplayBgm":true,"autoplayBgs":false,"battleback1Name":"","battleback2Name":"","bgm":{"name":"IntermezzoCavalleriaRusticana","pan":0,"pitch":100,"volume":90},"bgs":{"name":"","pan":0,"pitch":100,"volume":90},"disableDashing":false,"displayName":"孙氏药铺","encounterList":[],"encounterStep":30,"height":13,"note":"","parallaxLoopX":false,"parallaxLoopY":false,"parallaxName":"","parallaxShow":true,"parallaxSx":0,"parallaxSy":0,"scrollType":0,"specifyBattleback":false,"tilesetId":3,"width":17,
"data":[0,0,0,0,0,0,0,0,0,0,0,0,0,0,0,0,0,0,0,0,0,0,0,0,0,0,0,0,0,0,0,0,0,0,0,0,6787,6785,6785,6785,6785,6785,6785,6785,6785,6785,6785,6785,6789,0,0,0,0,6784,7138,7138,7138,7138,7138,7138,7138,7138,7138,7138,7138,6784,0,0,0,0,6784,7144,7144,7144,7144,7144,7144,7144,7144,7144,7144,7144,6784,0,0,0,0,6784,1555,1555,1555,1555,1555,1555,1555,1555,1555,1555,1555,6784,0,0,0,0,6784,1555,1555,1555,1555,1555,1555,1555,1555,1555,1555,1555,6784,0,0,0,0,6784,1555,1555,1555,1555,1555,1555,1555,1555,1555,1555,1555,6784,0,0,0,0,6784,1555,1555,1555,1555,1555,1555,1555,1555,1555,1555,1555,6784,0,0,0,0,6784,1555,1555,1555,1555,1555,1555,1555,1555,1555,1555,1555,6784,0,0,0,0,6793,6785,6785,6785,6785,6789,1555,1555,6787,6785,6785,6785,6791,0,0,0,0,0,0,0,0,0,6796,1555,1555,6796,0,0,0,0,0,0,0,0,0,0,0,0,0,0,0,0,0,0,0,0,0,0,0,0,0,0,0,0,0,0,0,0,0,0,0,0,0,0,0,0,0,0,0,0,0,0,0,0,0,0,0,0,0,0,0,0,0,0,0,0,0,0,0,0,0,0,0,0,0,0,0,0,0,0,0,0,0,0,0,0,0,0,0,0,0,0,0,0,0,0,0,0,0,0,0,0,0,0,0,0,0,0,0,0,0,0,0,0,0,0,0,0,0,0,0,0,0,0,0,0,0,0,0,0,0,0,0,0,0,0,0,0,0,0,0,0,0,0,0,0,0,0,0,0,0,3195,3185,3185,3185,3185,3185,3185,3185,3185,3185,3197,0,0,0,0,0,0,0,0,0,0,0,0,0,0,0,0,0,0,0,0,0,0,0,0,0,0,0,0,0,0,0,0,0,0,0,0,0,0,0,0,0,0,0,0,0,0,0,0,0,0,0,0,0,0,0,0,0,0,0,0,0,0,0,0,0,0,0,0,0,0,0,0,0,0,0,0,0,0,0,0,0,0,0,0,0,0,0,0,0,0,0,0,0,0,0,0,0,0,0,0,0,0,0,0,0,0,0,0,0,0,0,0,0,0,0,0,0,0,0,0,0,0,0,0,0,0,0,0,0,0,0,0,0,0,0,0,0,0,0,0,0,0,0,0,0,0,0,0,0,0,0,0,0,0,0,0,0,0,0,0,51,0,0,0,0,0,0,0,236,0,0,0,0,0,0,0,0,59,0,0,0,0,0,0,0,0,0,0,0,0,0,0,0,0,0,0,0,0,0,0,0,0,0,0,0,0,0,0,0,0,0,0,0,0,0,0,0,0,0,0,0,0,0,0,0,0,0,0,0,0,0,0,0,0,0,0,0,0,0,0,0,0,0,0,0,0,0,0,0,0,0,0,0,0,0,0,0,0,0,0,0,0,0,0,0,0,0,0,0,0,0,0,0,0,0,0,0,0,0,0,0,0,0,0,0,0,0,0,0,0,0,0,0,0,0,0,0,0,0,0,0,0,0,0,0,0,0,0,0,0,0,0,0,0,0,0,0,0,0,0,0,0,0,0,0,0,0,0,0,0,0,0,0,0,0,0,0,0,0,0,0,0,0,0,0,0,0,0,0,0,0,0,0,0,0,0,0,0,0,0,0,0,0,0,0,0,0,0,0,0,0,0,332,0,0,0,0,0,0,0,51,69,51,51,51,51,51,51,51,51,51,0,0,0,0,0,0,59,77,59,59,59,59,59,59,59,59,59,0,0,0,0,0,0,0,0,0,0,0,104,0,0,0,0,0,0,0,0,0,0,0,348,0,0,359,329,357,0,0,0,0,0,0,0,0,0,0,0,0,0,0,0,0,104,104,104,0,0,0,0,0,0,0,0,0,0,0,0,0,0,0,0,0,0,0,0,0,0,0,0,0,0,0,0,0,0,0,0,0,0,0,0,0,0,0,0,0,0,0,0,0,0,0,0,0,0,0,0,0,0,0,0,0,0,0,0,0,0,0,0,0,0,0,0,0,0,0,0,0,0,0,0,0,0,0,0,0,0,0,0,0,0,0,0,0,0,0,0,0,0,0,0,0,0,0,0,0,0,0,0,0,0,0,0,0,0,0,0,0,0,0,0,0,0,0,0,0,0,0,0,0,0,0,0,0,0,0,0,0,0,0,0,0,0,0,0,0,0,0,0,0,0,0,0,0,0,0,0,0,0,0,0,0,0,0,0,0,0,5,0,0,0,0,0,0,0,0,0,0,0,0,0,0,0,0,5,0,0,0,0,0,0,0,0,0,0,0,0,0,0,0,0,5,0,0,0,0,0,0,0,0,0,0,0,0,0,0,0,0,5,0,0,0,0,0,0,0,0,0,0,0,0,0,0,0,0,5,0,0,0,0,0,0,0,0,0,0,0,0,0,0,0,0,0,0,0,0,0,0,0,0,0,0,0,0,0,0,0,0,0,0,0,0,0,0,5,0,0,0,0,0,0,0,0,0,0,0,0,0,0,0,0,0,0,0,0,0,0,0,0,0,0,0,0,0,0,0,0,0,0,0,0,0,0,0,0,0,0,0,0,0,0,0,0,0,0,0,0,0,0,0,0,0,0,0,0,0,0,0,0,0,0,0,0,0,0,0,0,0,0,0,0,0,0,0,0,0,0,0,0,0,0,0,0,0,0,0,0,0,0,0,0,0,0,0,0,0,0,0,0,0,0,0,0,0,0,0,0,0,0,0,0,0,0,0,0,0,0,0,0,0,0,0,0,0,0,0,0,0,0,0,0,0,0,0,0,0,0,0,0,0,0,0,0,0,0,0,0,0,0,0,0,0,0,0,0,0,0,0,0,0,0,0,0,0,0,0,0,0,0,0,0,0,0,0,0,0,0,0,0,0,0,0,0,0,0,0,0,0,0,0,0,0,0,0,0,0,0,0,0,0,0,0,0,0,0,0,0,0,0,0,0,0,0,0,0,0,0,0,0,0,0,0,0,0,0,0,0,0,0,0,0,0,0,0,0,0,0,0,0,0,0],
"events":[
null,
{"id":1,"name":"孙中医","note":"","pages":[{"conditions":{"actorId":1,"actorValid":false,"itemId":1,"itemValid":false,"selfSwitchCh":"A","selfSwitchValid":false,"switch1Id":1,"switch1Valid":false,"switch2Id":1,"switch2Valid":false,"variableId":1,"variableValid":false,"variableValue":0},"directionFix":false,"image":{"tileId":0,"characterName":"XiaoSun","direction":2,"pattern":1,"characterIndex":0},"list":[{"code":0,"indent":0,"parameters":[]}],"moveFrequency":3,"moveRoute":{"list":[{"code":0,"parameters":[]}],"repeat":true,"skippable":false,"wait":false},"moveSpeed":3,"moveType":0,"priorityType":1,"stepAnime":false,"through":false,"trigger":0,"walkAnime":true}],"x":7,"y":6},
{"id":2,"name":"老范","note":"","pages":[{"conditions":{"actorId":1,"actorValid":false,"itemId":1,"itemValid":false,"selfSwitchCh":"A","selfSwitchValid":false,"switch1Id":1,"switch1Valid":false,"switch2Id":1,"switch2Valid":false,"variableId":1,"variableValid":false,"variableValue":0},"directionFix":false,"image":{"tileId":0,"characterName":"LaoFan","direction":8,"pattern":1,"characterIndex":0},"list":[{"code":101,"indent":0,"parameters":["XiaoDong",0,0,2]},{"code":401,"indent":0,"parameters":["范叔，我是老董他儿子，找章桂芳，你晓得不？"]},{"code":101,"indent":0,"parameters":["LaoFan",0,0,2]},{"code":401,"indent":0,"parameters":["啊？"]},{"code":101,"indent":0,"parameters":["XiaoSun",0,0,2]},{"code":401,"indent":0,"parameters":["章姨啊，我爹说过，咱老街坊，住这胡同和连丰胡同的岔口。"]},{"code":101,"indent":0,"parameters":["XiaoDong",0,0,2]},{"code":401,"indent":0,"parameters":["原来在那儿，谢了。"]},{"code":221,"indent":0,"parameters":[]},{"code":230,"indent":0,"parameters":[60]},{"code":201,"indent":0,"parameters":[0,55,0,10,6,0]},{"code":222,"indent":0,"parameters":[]},{"code":0,"indent":0,"parameters":[]}],"moveFrequency":3,"moveRoute":{"list":[{"code":0,"parameters":[]}],"repeat":true,"skippable":false,"wait":false},"moveSpeed":3,"moveType":0,"priorityType":1,"stepAnime":false,"through":false,"trigger":0,"walkAnime":true}],"x":7,"y":8},
null,
null,
null,
null,
null,
null
]
}